chemexpy/__init__.py
chemexpy/correlation_plot.py
chemexpy/data_prep.py
chemexpy/feature_check.py
chemexpy/feature_plot.py
chemexpy/feature_violinplots.py
chemexpy/molecule_check.py
chemexpy/normality_check.py
chemexpy/scatter_plot.py
chemexpy/similarity_dendogram.py
chemexpy/similarity_heatmap.py
chemexpy/similarity_search.py
chemexpy-1.0.10.dist-info/LICENSE.txt
chemexpy-1.0.10.dist-info/METADATA
chemexpy-1.0.10.dist-info/WHEEL
chemexpy-1.0.10.dist-info/top_level.txt
chemexpy-1.0.10.dist-info/RECORD
